Metadata-Version: 1.1
Name: vbuilder
Version: 0.0.0
Summary: Builder kampretcode
Home-page: https://github.com/kampretcode/dewibuilder
Author: kampretcode
Author-email: manorder123@gmail.com
License: MIT
Keywords: PDC,KAMPRETCODE,CUSTOMBUILDER,PYTHON,VAZIRIA,PACKAGE
Platform: UNKNOWN
Classifier: Development Status :: 5 - Production/Stable
Classifier: Intended Audience :: Developers
Classifier: Topic :: Software Development :: Build Tools
Classifier: License :: OSI Approved :: MIT License
Classifier: Programming Language :: Python :: 2.7
